sandbox_runtime/__init__.py
sandbox_runtime/cli.py
sandbox_runtime/config.py
sandbox_runtime/http_proxy.py
sandbox_runtime/linux_sandbox.py
sandbox_runtime/macos_sandbox.py
sandbox_runtime/manager.py
sandbox_runtime/runner.py
sandbox_runtime/sandbox_utils.py
sandbox_runtime/schemas.py
sandbox_runtime/seccomp.py
sandbox_runtime/socks_proxy.py
sandbox_runtime/violation_store.py
sandbox_runtime/server/README.md
sandbox_runtime/server/__init__.py
sandbox_runtime/server/config.py
sandbox_runtime/server/execution_manager.py
sandbox_runtime/server/mcp_server.py
sandbox_runtime/utils/__init__.py
sandbox_runtime/utils/debug.py
sandbox_runtime/utils/platform.py
sandbox_runtime/utils/ripgrep.py
sandbox_runtime-0.2.0.dist-info/METADATA
sandbox_runtime-0.2.0.dist-info/WHEEL
sandbox_runtime-0.2.0.dist-info/entry_points.txt
sandbox_runtime-0.2.0.dist-info/RECORD
