Metadata-Version: 2.4
Name: sandbox-runtime
Version: 0.2.0
Summary: A lightweight sandboxing tool for enforcing filesystem and network restrictions on arbitrary processes at the OS level
Author: Anthropic
License-Expression: MIT
Keywords: linux,macos,process-isolation,sandbox,security
Classifier: Development Status :: 4 - Beta
Classifier: Environment :: Console
Classifier: Intended Audience :: Developers
Classifier: License :: OSI Approved :: MIT License
Classifier: Operating System :: MacOS
Classifier: Operating System :: POSIX :: Linux
Classifier: Programming Language :: Python :: 3
Classifier: Programming Language :: Python :: 3.11
Classifier: Programming Language :: Python :: 3.12
Classifier: Topic :: Security
Classifier: Topic :: System :: Operating System Kernels :: Linux
Classifier: Typing :: Typed
Requires-Python: >=3.11
Requires-Dist: aiohttp>=3.9
Requires-Dist: click>=8.0
Requires-Dist: pydantic>=2.0
Requires-Dist: python-dotenv>=1.0
Provides-Extra: dev
Requires-Dist: aioresponses>=0.7; extra == 'dev'
Requires-Dist: httpx>=0.25; extra == 'dev'
Requires-Dist: matplotlib>=3.10; extra == 'dev'
Requires-Dist: mypy>=1.0; extra == 'dev'
Requires-Dist: numpy>=2.0; extra == 'dev'
Requires-Dist: pre-commit>=3.0; extra == 'dev'
Requires-Dist: pyright>=1.1; extra == 'dev'
Requires-Dist: pytest-asyncio>=0.23; extra == 'dev'
Requires-Dist: pytest-cov>=4.0; extra == 'dev'
Requires-Dist: pytest-timeout>=2.0; extra == 'dev'
Requires-Dist: pytest>=7.0; extra == 'dev'
Requires-Dist: ruff>=0.1; extra == 'dev'
Provides-Extra: server
Requires-Dist: loguru>=0.7; extra == 'server'
Requires-Dist: mcp>=1.0; extra == 'server'
Requires-Dist: uvicorn[standard]>=0.30; extra == 'server'
